yargen/__init__.py
yargen/yargen.py
yargen/yargen_entry.py
yargen-0.0.12.dist-info/LICENSE
yargen-0.0.12.dist-info/METADATA
yargen-0.0.12.dist-info/WHEEL
yargen-0.0.12.dist-info/top_level.txt
yargen-0.0.12.dist-info/RECORD
