Metadata-Version: 2.1
Name: yargen
Version: 0.0.12
Summary: 一個簡短的專案描述
Home-page: https://github.com/zhaoxinnZ/Yargen
Author: zhaoxinnZ
Author-email: zhaoxinzhang0429@gmail.com
Classifier: Programming Language :: Python :: 3
Classifier: License :: OSI Approved :: MIT License
Classifier: Operating System :: OS Independent
Requires-Python: >=3.6
License-File: LICENSE
